Workbook

Sheet ℹ Instructions
B2: MAINTENANCE PLANNING TOOL — USER GUIDE
B5: OVERVIEW
C6: This workbook contains 5 sheets: Instructions, Annual Planner (Gantt), Work Order Register, Resource Allocation, and KPI Summary. All sheets link together automatically.
B8: STEP 1 — Settings
C9: Go to the 'Settings' tab. Enter your facility name, planning year, total planned hours per month, and the list of technicians. These feed into the Resource sheet.
B11: STEP 2 — Annual Planner
C12: Go to '📅 Annual Planner'. Add each maintenance task: enter the Task ID, description, equipment tag, type (PM/PdM/CBM/Overhaul), responsible person, planned start week, and duration in weeks. The Gantt bars fill automatically.
B14: STEP 3 — Work Orders
C15: Go to '📋 Work Orders'. Log each work order as it is raised: WO number, linked task, equipment, priority, status, estimated and actual hours, and cost. Status dropdown controls the row colour (Planned / In Progress / Complete / Overdue / Cancelled).
B17: STEP 4 — Resource Allocation
C18: Go to '👥 Resources'. This sheet shows planned hours per technician per month, compared to their available hours. Over-allocated months are highlighted in red automatically.
B20: STEP 5 — KPI Summary
C21: Go to '📊 KPIs'. All metrics (PM Compliance, Schedule Adherence, Backlog, Cost Variance) calculate automatically from the Work Order sheet. No manual entry needed.
B23: COLOUR CODING
C24: Yellow cells = manual input required. Blue cells = auto-calculated (do not edit). Green rows = Complete. Red rows = Overdue. Orange rows = In Progress. Gantt bars: dark fill = planned window, green fill = complete.
B26: CONTACT
C27: Template by Katleho Khoarane | Mechanical Engineer | MEng Candidate — CUT | Turbomachinery · Mining · Energy | linkedin.com/in/katleho-khoarane

Sheet ⚙ Settings
B2: SETTINGS — Edit yellow cells only
B4: Facility Name | C4: Acme Mining — Plant A
B5: Planning Year | C5: 2025
B6: Total weeks in year | C6: 52
B7: Std hours/day | C7: 8
B8: Std working days/month | C8: 22
B10: TECHNICIANS (one per row below)
B11: T. Mokoena
B12: S. Dlamini
B13: R. Botha
B14: K. Sithole
B15: J. van Wyk
B16: A. Mahlangu
B19: NAMED_TECH_START

Sheet 📅 Annual Planner
B2: ANNUAL MAINTENANCE PLANNER — GANTT VIEW
K3: JAN | O3: FEB | S3: MAR | X3: APR | AB3: MAY | AF3: JUN | AJ3: JUL | AO3: AUG | AS3: SEP | AW3: OCT | BB3: NOV | BF3: DEC
B4: Task ID | C4: Description | D4: Equipment | E4: Type | F4: Responsible | G4: Start Week | H4: Duration (wks) | I4: Status | J4: Priority | K4: 1 | L4: 2 | M4: 3 | N4: 4 | O4: 5 | P4: 6 | Q4: 7 | R4: 8 | S4: 9 | T4: 10 | U4: 11 | V4: 12 | W4: 13 | X4: 14 | Y4: 15 | Z4: 16 | AA4: 17 | AB4: 18 | AC4: 19 | AD4: 20 | AE4: 21 | AF4: 22 | AG4: 23 | AH4: 24 | AI4: 25 | AJ4: 26 | AK4: 27 | AL4: 28 | AM4: 29 | AN4: 30 | AO4: 31 | AP4: 32 | AQ4: 33 | AR4: 34 | AS4: 35 | AT4: 36 | AU4: 37 | AV4: 38 | AW4: 39 | AX4: 40 | AY4: 41 | AZ4: 42 | BA4: 43 | BB4: 44 | BC4: 45 | BD4: 46 | BE4: 47 | BF4: 48 | BG4: 49 | BH4: 50 | BI4: 51 | BJ4: 52
B5: T-001 | C5: 30,000hr PM — Feed Pump P-101 | D5: P-101 | E5: PM | F5: T. Mokoena | G5: 1 | H5: 1 | I5: Planned | J5: High | K5: █
B6: T-002 | C6: Gearbox oil change — GB-001 | D6: GB-001 | E6: PM | F6: S. Dlamini | G6: 2 | H6: 1 | I6: Planned | J6: Medium | L6: █
B7: T-003 | C7: Conveyor belt inspection — CV-001 | D7: CV-001 | E7: Inspection | F7: R. Botha | G7: 3 | H7: 1 | I7: Planned | J7: High | M7: █
B8: T-004 | C8: Vibration analysis — M-101 | D8: M-101 | E8: PdM | F8: K. Sithole | G8: 4 | H8: 1 | I8: Planned | J8: High | N8: █
B9: T-005 | C9: Crusher overhaul | D9: M-101 | E9: Overhaul | F9: T. Mokoena | G9: 5 | H9: 4 | I9: Planned | J9: Critical | O9: █ | P9: █ | Q9: █ | R9: █
B10: T-006 | C10: Lubrication round — all pumps | D10: P-101 | E10: Lubrication | F10: J. van Wyk | G10: 1 | H10: 1 | I10: Planned | J10: Low | K10: █
B11: T-007 | C11: Ball mill liner replacement | D11: M-102 | E11: Overhaul | F11: A. Mahlangu | G11: 12 | H11: 3 | I11: Planned | J11: Critical | V11: █ | W11: █ | X11: █
B12: T-008 | C12: Cooling fan bearing replacement | D12: FN-001 | E12: PM | F12: R. Botha | G12: 8 | H12: 1 | I12: Planned | J12: Medium | R12: █
B13: T-009 | C13: Compressor valve overhaul | D13: C-101 | E13: Overhaul | F13: S. Dlamini | G13: 16 | H13: 2 | I13: Planned | J13: High | Z13: █ | AA13: █
B14: T-010 | C14: Tailings pump impeller check | D14: P-102 | E14: Inspection | F14: K. Sithole | G14: 20 | H14: 1 | I14: Planned | J14: Medium | AD14: █
B15: T-011 | C15: Conveyor CV-002 belt tension | D15: CV-002 | E15: PM | F15: J. van Wyk | G15: 24 | H15: 1 | I15: Planned | J15: Low | AH15: █
B16: T-012 | C16: Gearbox GB-002 oil analysis | D16: GB-002 | E16: PdM | F16: T. Mokoena | G16: 26 | H16: 1 | I16: Planned | J16: Medium | AJ16: █
B17: T-013 | C17: Motor alignment check — M-101 | D17: M-101 | E17: Inspection | F17: A. Mahlangu | G17: 30 | H17: 1 | I17: Planned | J17: High | AN17: █
B18: T-014 | C18: Annual safety valve test | D18: C-101 | E18: Inspection | F18: S. Dlamini | G18: 40 | H18: 1 | I18: Planned | J18: Critical | AX18: █
B19: T-015 | C19: Year-end full facility inspection | D19: ALL | E19: Inspection | F19: T. Mokoena | G19: 50 | H19: 2 | I19: Planned | J19: Critical | BH19: █ | BI19: █
B57: LEGEND — Task Type: | C57: PM | D57: PdM | E57: CBM | F57: Overhaul | G57: Inspection | H57: Lubrication | I57: Calibration

Sheet 📋 Work Orders
B2: WORK ORDER REGISTER
B3: ► Yellow cells = manual input | Blue cells = auto-calculated | Status dropdown controls row colour
B4: WO Number | C4: Task ID | D4: Description | E4: Equipment | F4: Priority | G4: Status | H4: Assigned To | I4: Planned Date | J4: Completion Date | K4: Est. Hours | L4: Actual Hours | M4: Est. Cost (R)
B5: WO-2025-001 | C5: T-001 | D5: 30,000hr PM — Feed Pump P-101 | E5: P-101 | F5: High | G5: Planned | H5: T. Mokoena | K5: 8 | L5: 0 | M5: 3500
B6: WO-2025-002 | C6: T-002 | D6: Gearbox oil change GB-001 | E6: GB-001 | F6: Medium | G6: Planned | H6: S. Dlamini | K6: 4 | L6: 0 | M6: 800
B7: WO-2025-003 | C7: T-003 | D7: Conveyor belt inspection CV-001 | E7: CV-001 | F7: High | G7: Planned | H7: R. Botha | K7: 6 | L7: 0 | M7: 1200
B8: WO-2025-004 | C8: T-004 | D8: Vibration analysis M-101 | E8: M-101 | F8: High | G8: Planned | H8: K. Sithole | K8: 3 | L8: 0 | M8: 500
B9: WO-2025-005 | C9: T-005 | D9: Crusher overhaul | E9: M-101 | F9: Critical | G9: Planned | H9: T. Mokoena | K9: 80 | L9: 0 | M9: 45000
B10: WO-2025-006 | C10: T-006 | D10: Lubrication round — all pumps | E10: P-101 | F10: Low | G10: Planned | H10: J. van Wyk | K10: 4 | L10: 0 | M10: 300
B11: WO-2025-007 | C11: T-007 | D11: Ball mill liner replacement | E11: M-102 | F11: Critical | G11: Planned | H11: A. Mahlangu | K11: 60 | L11: 0 | M11: 38000
B12: WO-2025-008 | C12: T-008 | D12: Cooling fan bearing replacement | E12: FN-001 | F12: Medium | G12: Planned | H12: R. Botha | K12: 8 | L12: 0 | M12: 2200
B13: WO-2025-009 | C13: T-009 | D13: Compressor valve overhaul | E13: C-101 | F13: High | G13: Planned | H13: S. Dlamini | K13: 16 | L13: 0 | M13: 9500
B14: WO-2025-010 | C14: T-010 | D14: Tailings pump impeller check | E14: P-102 | F14: Medium | G14: Planned | H14: K. Sithole | K14: 6 | L14: 0 | M14: 1800
B105: TOTALS | K105: =SUM(K5:K104) -> 195 | L105: =SUM(L5:L104) -> 0 | M105: =SUM(M5:M104) -> 102800

Sheet 👥 Resources
B2: RESOURCE ALLOCATION — Hours per Technician per Month
B4: Technician | C4: Jan | D4: Feb | E4: Mar | F4: Apr | G4: May | H4: Jun | I4: Jul | J4: Aug | K4: Sep | L4: Oct | M4: Nov | N4: Dec | O4: TOTAL
B5: T. Mokoena | C5: 0 | D5: 0 | E5: 0 | F5: 0 | G5: 0 | H5: 0 | I5: 0 | J5: 0 | K5: 0 | L5: 0 | M5: 0 | N5: 0 | O5: =SUM(C5:N5) -> 0
B6: Available hrs | C6: 176 | D6: 176 | E6: 176 | F6: 176 | G6: 176 | H6: 176 | I6: 176 | J6: 176 | K6: 176 | L6: 176 | M6: 176 | N6: 176 | O6: =176*12 -> 2112
B8: S. Dlamini | C8: 0 | D8: 0 | E8: 0 | F8: 0 | G8: 0 | H8: 0 | I8: 0 | J8: 0 | K8: 0 | L8: 0 | M8: 0 | N8: 0 | O8: =SUM(C8:N8) -> 0
B9: Available hrs | C9: 176 | D9: 176 | E9: 176 | F9: 176 | G9: 176 | H9: 176 | I9: 176 | J9: 176 | K9: 176 | L9: 176 | M9: 176 | N9: 176 | O9: =176*12 -> 2112
B11: R. Botha | C11: 0 | D11: 0 | E11: 0 | F11: 0 | G11: 0 | H11: 0 | I11: 0 | J11: 0 | K11: 0 | L11: 0 | M11: 0 | N11: 0 | O11: =SUM(C11:N11) -> 0
B12: Available hrs | C12: 176 | D12: 176 | E12: 176 | F12: 176 | G12: 176 | H12: 176 | I12: 176 | J12: 176 | K12: 176 | L12: 176 | M12: 176 | N12: 176 | O12: =176*12 -> 2112
B14: K. Sithole | C14: 0 | D14: 0 | E14: 0 | F14: 0 | G14: 0 | H14: 0 | I14: 0 | J14: 0 | K14: 0 | L14: 0 | M14: 0 | N14: 0 | O14: =SUM(C14:N14) -> 0
B15: Available hrs | C15: 176 | D15: 176 | E15: 176 | F15: 176 | G15: 176 | H15: 176 | I15: 176 | J15: 176 | K15: 176 | L15: 176 | M15: 176 | N15: 176 | O15: =176*12 -> 2112
B17: J. van Wyk | C17: 0 | D17: 0 | E17: 0 | F17: 0 | G17: 0 | H17: 0 | I17: 0 | J17: 0 | K17: 0 | L17: 0 | M17: 0 | N17: 0 | O17: =SUM(C17:N17) -> 0
B18: Available hrs | C18: 176 | D18: 176 | E18: 176 | F18: 176 | G18: 176 | H18: 176 | I18: 176 | J18: 176 | K18: 176 | L18: 176 | M18: 176 | N18: 176 | O18: =176*12 -> 2112
B20: A. Mahlangu | C20: 0 | D20: 0 | E20: 0 | F20: 0 | G20: 0 | H20: 0 | I20: 0 | J20: 0 | K20: 0 | L20: 0 | M20: 0 | N20: 0 | O20: =SUM(C20:N20) -> 0
B21: Available hrs | C21: 176 | D21: 176 | E21: 176 | F21: 176 | G21: 176 | H21: 176 | I21: 176 | J21: 176 | K21: 176 | L21: 176 | M21: 176 | N21: 176 | O21: =176*12 -> 2112

Sheet 📊 KPIs
B2: KPI SUMMARY — Auto-calculated from Work Order Register
B5: PM COMPLIANCE | C5: % of planned WOs completed on time | D5: =IFERROR(COUNTIFS('📋 Work Orders'!G5:G104,"Complete")/COUNTA('📋 Work Orders'!B5:B104),0) -> 0 | E5: Target: ≥ 85%
B7: SCHEDULE ADHERENCE | C7: WOs completed vs total WOs raised | D7: =IFERROR(COUNTIF('📋 Work Orders'!G5:G104,"Complete")/COUNTA('📋 Work Orders'!B5:B104),0) -> 0 | E7: Target: ≥ 90%
B9: TOTAL WORK ORDERS | C9: All WOs in the register | D9: =COUNTA('📋 Work Orders'!B5:B104) -> 10
B11: OPEN WORK ORDERS | C11: WOs with status = Planned or In Progress | D11: =COUNTIFS('📋 Work Orders'!G5:G104,"Planned")+COUNTIFS('📋 Work Orders'!G5:G104,"In Progress") -> 10
B13: OVERDUE WORK ORDERS | C13: WOs with status = Overdue | D13: =COUNTIF('📋 Work Orders'!G5:G104,"Overdue") -> 0 | E13: Target: 0
B15: BACKLOG HOURS | C15: Est. hours on open + overdue WOs | D15: =SUMPRODUCT((('📋 Work Orders'!G5:G104="Planned")+('📋 Work Orders'!G5:G104="Overdue")>0)*'📋 Work Orders'!K5:K104) -> 195
B17: TOTAL EST. COST | C17: Sum of all estimated costs (R) | D17: ='📋 Work Orders'!M105 -> 102800
B19: CRITICAL WOs OPEN | C19: Priority = Critical AND status ≠ Complete | D19: =COUNTIFS('📋 Work Orders'!F5:F104,"Critical",'📋 Work Orders'!G5:G104,"<>Complete") -> 2 | E19: Target: 0

Sheet Premium Guide
A1: Maintenance Planning Excel — PREMIUM UPGRADE GUIDE
A2: Original template preserved. Added premium sheets turn the file into a semi-automated maintenance management tool.
A4: Step | B4: What to do | C4: Outcome
A5: 1 | B5: Enter field data | C5: Complete the original inspection/report sheet. Yellow cells and result columns are input fields.
A6: 2 | B6: Use dropdowns | C6: Use standardised results, priority, status, criticality and RCA decision fields to keep data clean.
A7: 3 | B7: Review dashboard | C7: Open the dashboard/summary sheet to view compliance, open actions, overdue actions and management risk indicators.
A8: 4 | B8: Close actions | C8: Transfer defects/recommendations to the Action Tracker with owner, due date, status and verification evidence.
A9: 5 | B9: Issue report | C9: Use the original form for site records and the added registers for meetings, audits and maintenance planning.
A12: Upgrades Implemented
A13: • PM frequency engine added to generate next due dates from daily/weekly/monthly/quarterly/annual frequencies.
A14: • Backlog ageing matrix added for open work by 0–7, 8–30, 31–60 and 60+ days.
A15: • Shutdown planner added for tasks, dependencies, permits, spares, resources and readiness.
A16: • Cost variance tracker added for budget vs actual cost control.
A17: • Premium executive dashboard added for PM compliance, schedule compliance, backlog and action status.

Sheet Lists
A1: CONTROL LISTS / DROPDOWNS
A2: Edit these lists if your site uses different status, priority, failure mode or criticality labels.
A4: Status | B4: Priority | C4: Result | D4: Severity | E4: Failure Mode | F4: Criticality | G4: Shift | H4: RCA Required
A5: Open | B5: Critical | C5: ✓ | D5: 1 | E5: Mechanical | F5: A - Critical | G5: Day | H5: Yes
A6: In Progress | B6: High | C6: ✗ | D6: 2 | E6: Electrical | F6: B - Important | G6: Night | H6: No
A7: Complete | B7: Medium | C7: N/A | D7: 3 | E7: Lubrication | F7: C - General | G7: A | H7: TBC
A8: Overdue | B8: Low | C8: Monitor | D8: 4 | E8: Hydraulic | G8: B
A9: Deferred | B9: Monitor | D9: 5 | E9: Pneumatic | G9: C
A10: Cancelled | E10: Instrumentation | G10: D
A11: Verified | E11: Process
E12: Operator
E13: Design
E14: Unknown

Sheet Action Tracker
A1: ACTION TRACKER
A2: Central register for defects, recommendations, close-out dates, and verification.
A4: Source/Sheet | B4: Asset / Equipment | C4: Finding / Defect | D4: Risk / Impact | E4: Priority | F4: Responsible Person | G4: Due Date | H4: Status | I4: Close-out Date | J4: Verification / Evidence | K4: Days Overdue
H5: Open | K5: =IF(AND(G5<>"",H5<>"Complete",H5<>"Verified"),MAX(0,TODAY()-G5),0) -> 0
H6: Open | K6: =IF(AND(G6<>"",H6<>"Complete",H6<>"Verified"),MAX(0,TODAY()-G6),0) -> 0
H7: Open | K7: =IF(AND(G7<>"",H7<>"Complete",H7<>"Verified"),MAX(0,TODAY()-G7),0) -> 0
H8: Open | K8: =IF(AND(G8<>"",H8<>"Complete",H8<>"Verified"),MAX(0,TODAY()-G8),0) -> 0
H9: Open | K9: =IF(AND(G9<>"",H9<>"Complete",H9<>"Verified"),MAX(0,TODAY()-G9),0) -> 0
H10: Open | K10: =IF(AND(G10<>"",H10<>"Complete",H10<>"Verified"),MAX(0,TODAY()-G10),0) -> 0
H11: Open | K11: =IF(AND(G11<>"",H11<>"Complete",H11<>"Verified"),MAX(0,TODAY()-G11),0) -> 0
H12: Open | K12: =IF(AND(G12<>"",H12<>"Complete",H12<>"Verified"),MAX(0,TODAY()-G12),0) -> 0
H13: Open | K13: =IF(AND(G13<>"",H13<>"Complete",H13<>"Verified"),MAX(0,TODAY()-G13),0) -> 0
H14: Open | K14: =IF(AND(G14<>"",H14<>"Complete",H14<>"Verified"),MAX(0,TODAY()-G14),0) -> 0
H15: Open | K15: =IF(AND(G15<>"",H15<>"Complete",H15<>"Verified"),MAX(0,TODAY()-G15),0) -> 0
H16: Open | K16: =IF(AND(G16<>"",H16<>"Complete",H16<>"Verified"),MAX(0,TODAY()-G16),0) -> 0
... H34: Open | K34: =IF(AND(G34<>"",H34<>"Complete",H34<>"Verified"),MAX(0,TODAY()-G34),0) -> 0

Sheet PM Frequency Engine
A1: PM FREQUENCY ENGINE
A2: Build a master PM register and calculate next due dates automatically.
A4: PM ID | B4: Equipment Tag | C4: Task Description | D4: Frequency | E4: Last Done | F4: Next Due | G4: Criticality | H4: Responsible | I4: WO Template | J4: Status | K4: Action Required | L4: Notes | M4: Running Hours Basis
A5: PM-001 | D5: M | F5: =IF(E5="","",E5+IF(D5="D",1,IF(D5="W",7,IF(D5="M",30,IF(D5="Q",91,IF(D5="A",365,IF(D5="6M",182,30))))))) | J5: Open
A6: PM-002 | F6: =IF(E6="","",E6+IF(D6="D",1,IF(D6="W",7,IF(D6="M",30,IF(D6="Q",91,IF(D6="A",365,IF(D6="6M",182,30))))))) | J6: Open
A7: PM-003 | F7: =IF(E7="","",E7+IF(D7="D",1,IF(D7="W",7,IF(D7="M",30,IF(D7="Q",91,IF(D7="A",365,IF(D7="6M",182,30))))))) | J7: Open
A8: PM-004 | F8: =IF(E8="","",E8+IF(D8="D",1,IF(D8="W",7,IF(D8="M",30,IF(D8="Q",91,IF(D8="A",365,IF(D8="6M",182,30))))))) | J8: Open
A9: PM-005 | F9: =IF(E9="","",E9+IF(D9="D",1,IF(D9="W",7,IF(D9="M",30,IF(D9="Q",91,IF(D9="A",365,IF(D9="6M",182,30))))))) | J9: Open
A10: PM-006 | F10: =IF(E10="","",E10+IF(D10="D",1,IF(D10="W",7,IF(D10="M",30,IF(D10="Q",91,IF(D10="A",365,IF(D10="6M",182,30))))))) | J10: Open
A11: PM-007 | F11: =IF(E11="","",E11+IF(D11="D",1,IF(D11="W",7,IF(D11="M",30,IF(D11="Q",91,IF(D11="A",365,IF(D11="6M",182,30))))))) | J11: Open
A12: PM-008 | F12: =IF(E12="","",E12+IF(D12="D",1,IF(D12="W",7,IF(D12="M",30,IF(D12="Q",91,IF(D12="A",365,IF(D12="6M",182,30))))))) | J12: Open
A13: PM-009 | F13: =IF(E13="","",E13+IF(D13="D",1,IF(D13="W",7,IF(D13="M",30,IF(D13="Q",91,IF(D13="A",365,IF(D13="6M",182,30))))))) | J13: Open
A14: PM-010 | F14: =IF(E14="","",E14+IF(D14="D",1,IF(D14="W",7,IF(D14="M",30,IF(D14="Q",91,IF(D14="A",365,IF(D14="6M",182,30))))))) | J14: Open
A15: PM-011 | F15: =IF(E15="","",E15+IF(D15="D",1,IF(D15="W",7,IF(D15="M",30,IF(D15="Q",91,IF(D15="A",365,IF(D15="6M",182,30))))))) | J15: Open
A16: PM-012 | F16: =IF(E16="","",E16+IF(D16="D",1,IF(D16="W",7,IF(D16="M",30,IF(D16="Q",91,IF(D16="A",365,IF(D16="6M",182,30))))))) | J16: Open
A17: PM-013 | F17: =IF(E17="","",E17+IF(D17="D",1,IF(D17="W",7,IF(D17="M",30,IF(D17="Q",91,IF(D17="A",365,IF(D17="6M",182,30))))))) | J17: Open
... A34: PM-030 | F34: =IF(E34="","",E34+IF(D34="D",1,IF(D34="W",7,IF(D34="M",30,IF(D34="Q",91,IF(D34="A",365,IF(D34="6M",182,30))))))) | J34: Open

Sheet Backlog Aging
A1: BACKLOG AGEING MATRIX
A2: Track open work orders by age band and priority.
A4: WO Number | B4: Equipment Tag | C4: Description | D4: Priority | E4: Date Raised | F4: Age (days) | G4: Age Band | H4: Status | I4: Responsible | J4: Action
F5: =IF(E5="","",TODAY()-E5) | G5: =IF(F5="","",IF(F5<=7,"0-7 days",IF(F5<=30,"8-30 days",IF(F5<=60,"31-60 days","60+ days")))) | H5: Open
F6: =IF(E6="","",TODAY()-E6) | G6: =IF(F6="","",IF(F6<=7,"0-7 days",IF(F6<=30,"8-30 days",IF(F6<=60,"31-60 days","60+ days")))) | H6: Open
F7: =IF(E7="","",TODAY()-E7) | G7: =IF(F7="","",IF(F7<=7,"0-7 days",IF(F7<=30,"8-30 days",IF(F7<=60,"31-60 days","60+ days")))) | H7: Open
F8: =IF(E8="","",TODAY()-E8) | G8: =IF(F8="","",IF(F8<=7,"0-7 days",IF(F8<=30,"8-30 days",IF(F8<=60,"31-60 days","60+ days")))) | H8: Open
F9: =IF(E9="","",TODAY()-E9) | G9: =IF(F9="","",IF(F9<=7,"0-7 days",IF(F9<=30,"8-30 days",IF(F9<=60,"31-60 days","60+ days")))) | H9: Open
F10: =IF(E10="","",TODAY()-E10) | G10: =IF(F10="","",IF(F10<=7,"0-7 days",IF(F10<=30,"8-30 days",IF(F10<=60,"31-60 days","60+ days")))) | H10: Open
F11: =IF(E11="","",TODAY()-E11) | G11: =IF(F11="","",IF(F11<=7,"0-7 days",IF(F11<=30,"8-30 days",IF(F11<=60,"31-60 days","60+ days")))) | H11: Open
F12: =IF(E12="","",TODAY()-E12) | G12: =IF(F12="","",IF(F12<=7,"0-7 days",IF(F12<=30,"8-30 days",IF(F12<=60,"31-60 days","60+ days")))) | H12: Open
F13: =IF(E13="","",TODAY()-E13) | G13: =IF(F13="","",IF(F13<=7,"0-7 days",IF(F13<=30,"8-30 days",IF(F13<=60,"31-60 days","60+ days")))) | H13: Open
F14: =IF(E14="","",TODAY()-E14) | G14: =IF(F14="","",IF(F14<=7,"0-7 days",IF(F14<=30,"8-30 days",IF(F14<=60,"31-60 days","60+ days")))) | H14: Open
F15: =IF(E15="","",TODAY()-E15) | G15: =IF(F15="","",IF(F15<=7,"0-7 days",IF(F15<=30,"8-30 days",IF(F15<=60,"31-60 days","60+ days")))) | H15: Open
F16: =IF(E16="","",TODAY()-E16) | G16: =IF(F16="","",IF(F16<=7,"0-7 days",IF(F16<=30,"8-30 days",IF(F16<=60,"31-60 days","60+ days")))) | H16: Open
... F34: =IF(E34="","",TODAY()-E34) | G34: =IF(F34="","",IF(F34<=7,"0-7 days",IF(F34<=30,"8-30 days",IF(F34<=60,"31-60 days","60+ days")))) | H34: Open

Sheet Shutdown Planner
A1: SHUTDOWN PLANNING MODULE
A2: Plan task sequence, dependencies, permits, spares, resources and readiness.
A4: Shutdown ID | B4: Task ID | C4: Task Description | D4: Equipment | E4: Predecessor | F4: Start | G4: Finish | H4: Duration hrs | I4: Permit Required? | J4: Spares Ready? | K4: Resources Ready? | L4: Risk | M4: Status | N4: Comments
A5: SD-001 | I5: No | J5: No | K5: No | L5: Medium | M5: Planned
A6: SD-001 | I6: No | J6: No | K6: No | L6: Medium | M6: Planned
A7: SD-001 | I7: No | J7: No | K7: No | L7: Medium | M7: Planned
A8: SD-001 | I8: No | J8: No | K8: No | L8: Medium | M8: Planned
A9: SD-001 | I9: No | J9: No | K9: No | L9: Medium | M9: Planned
A10: SD-001 | I10: No | J10: No | K10: No | L10: Medium | M10: Planned
A11: SD-001 | I11: No | J11: No | K11: No | L11: Medium | M11: Planned
A12: SD-001 | I12: No | J12: No | K12: No | L12: Medium | M12: Planned
A13: SD-001 | I13: No | J13: No | K13: No | L13: Medium | M13: Planned
A14: SD-001 | I14: No | J14: No | K14: No | L14: Medium | M14: Planned
A15: SD-001 | I15: No | J15: No | K15: No | L15: Medium | M15: Planned
A16: SD-001 | I16: No | J16: No | K16: No | L16: Medium | M16: Planned
... A29: SD-001 | I29: No | J29: No | K29: No | L29: Medium | M29: Planned

Sheet Cost Variance
A1: MAINTENANCE COST PLAN VS ACTUAL
A2: Compare planned budget to actual cost by work order or task.
A4: WO / Task | B4: Equipment | C4: Cost Category | D4: Planned Cost | E4: Actual Cost | F4: Variance | G4: Variance % | H4: Reason | I4: Owner | J4: Corrective Action | K4: Status
F5: =IF(OR(D5="",E5=""),"",E5-D5) | G5: =IFERROR(F5/D5,"") | K5: Open
F6: =IF(OR(D6="",E6=""),"",E6-D6) | G6: =IFERROR(F6/D6,"") | K6: Open
F7: =IF(OR(D7="",E7=""),"",E7-D7) | G7: =IFERROR(F7/D7,"") | K7: Open
F8: =IF(OR(D8="",E8=""),"",E8-D8) | G8: =IFERROR(F8/D8,"") | K8: Open
F9: =IF(OR(D9="",E9=""),"",E9-D9) | G9: =IFERROR(F9/D9,"") | K9: Open
F10: =IF(OR(D10="",E10=""),"",E10-D10) | G10: =IFERROR(F10/D10,"") | K10: Open
F11: =IF(OR(D11="",E11=""),"",E11-D11) | G11: =IFERROR(F11/D11,"") | K11: Open
F12: =IF(OR(D12="",E12=""),"",E12-D12) | G12: =IFERROR(F12/D12,"") | K12: Open
F13: =IF(OR(D13="",E13=""),"",E13-D13) | G13: =IFERROR(F13/D13,"") | K13: Open
F14: =IF(OR(D14="",E14=""),"",E14-D14) | G14: =IFERROR(F14/D14,"") | K14: Open
F15: =IF(OR(D15="",E15=""),"",E15-D15) | G15: =IFERROR(F15/D15,"") | K15: Open
F16: =IF(OR(D16="",E16=""),"",E16-D16) | G16: =IFERROR(F16/D16,"") | K16: Open
... F34: =IF(OR(D34="",E34=""),"",E34-D34) | G34: =IFERROR(F34/D34,"") | K34: Open

Sheet Premium Executive Dashboard
A1: MAINTENANCE PLANNING EXECUTIVE DASHBOARD
A2: Management summary across PM frequency, backlog, shutdown readiness and action close-out.
A4: Metric | B4: Value | C4: Interpretation
A5: PM tasks registered | B5: =COUNTA('PM Frequency Engine'!A5:A34) -> 30 | C5: Rows in PM master register
A6: PM overdue | B6: =COUNTIF('PM Frequency Engine'!F5:F34,"<"&TODAY()) -> 0 | C6: Next due dates before today
A7: Backlog open | B7: =COUNTIFS('Backlog Aging'!H:H,"<>Complete",'Backlog Aging'!A:A,"<>") -> 3 | C7: Work not complete
A8: Backlog 60+ days | B8: =COUNTIF('Backlog Aging'!G:G,"60+ days") -> 0 | C8: High ageing risk
A9: Shutdown tasks not ready | B9: =COUNTIF('Shutdown Planner'!M:M,"Planned")+COUNTIF('Shutdown Planner'!M:M,"Delayed") -> 25 | C9: Readiness attention
A10: Cost overrun total | B10: =SUMIF('Cost Variance'!F:F,">0",'Cost Variance'!F:F) -> 0 | C10: Actual cost above plan
A11: Open actions | B11: =COUNTIFS('Action Tracker'!H:H,"<>Complete",'Action Tracker'!H:H,"<>Verified",'Action Tracker'!A:A,"<>") -> 3 | C11: Action tracker not closed
A12: Overall status | B12: =IF(B6>0,"BACKLOG AGEING RISK",IF(B5>0,"PM OVERDUE","CONTROLLED")) -> PM OVERDUE | C12: Management interpretation
